LICENSE
MANIFEST.in
README.md
setup.cfg
setup.py
conf/stream_repeater.yaml
stream_repeater/__init__.py
stream_repeater/config.py
stream_repeater/models.py
stream_repeater/options.py
stream_repeater/views.py
stream_repeater.egg-info/PKG-INFO
stream_repeater.egg-info/SOURCES.txt
stream_repeater.egg-info/dependency_links.txt
stream_repeater.egg-info/entry_points.txt
stream_repeater.egg-info/requires.txt
stream_repeater.egg-info/top_level.txt