Metadata-Version: 2.1
Name: stream-repeater
Version: 0.1.0
Summary: Converts and uploads saved streams to remote platforms
Home-page: https://github.com/frozenfoxx/stream_repeater
Author: FrozenFOXX
Author-email: frozenfoxx@churchoffoxx.net
License: UNKNOWN
Download-URL: https://github.com/frozenfoxx/stream_repeater/archive/refs/tags/0.1.0.tar.gz
Platform: UNKNOWN
Classifier: Programming Language :: Python :: 3
Classifier: License :: OSI Approved :: Apache Software License
Classifier: Operating System :: OS Independent
License-File: LICENSE
